[
	{
		"Category": "PhotoFrame",
		"Color": null,
		"Title": "해바라기 그림 대형 개업 거실 황금 돈들어오는 액자",
		"Link": "https://search.shopping.naver.com/gate.nhn?id=83708454595",
		"Image": "https://shopping-phinf.pstatic.net/main_8370845/83708454595.5.jpg",
		"Brand": "",
		"Price": "69480"
	},
	{
		"Category": "PhotoFrame",
		"Color": null,
		"Title": "해바라기 그림 액자 선플라워 A",
		"Link": "https://search.shopping.naver.com/gate.nhn?id=31775561554",
		"Image": "https://shopping-phinf.pstatic.net/main_3177556/31775561554.20220728122810.jpg",
		"Brand": "",
		"Price": "26900"
	},
	{
		"Category": "PhotoFrame",
		"Color": null,
		"Title": "아르셰 LED 무드 조명 거실 캔버스액자 인테리어 야경",
		"Link": "https://search.shopping.naver.com/gate.nhn?id=23726575002",
		"Image": "https://shopping-phinf.pstatic.net/main_2372657/23726575002.20200825144912.jpg",
		"Brand": "아르셰",
		"Price": "19700"
	},
	{
		"Category": "PhotoFrame",
		"Color": null,
		"Title": "황금돈나무 인테리어액자 캔버스 포스터 그림 액자 A",
		"Link": "https://search.shopping.naver.com/gate.nhn?id=32879746589",
		"Image": "https://shopping-phinf.pstatic.net/main_3287974/32879746589.20220611122054.jpg",
		"Brand": "",
		"Price": "15900"
	},
	{
		"Category": "PhotoFrame",
		"Color": null,
		"Title": "사이즈 업 인테리어 액자 해바라기 그림 액자 카페 식당 개업 선물",
		"Link": "https://search.shopping.naver.com/gate.nhn?id=84086483742",
		"Image": "https://shopping-phinf.pstatic.net/main_8408648/84086483742.jpg",
		"Brand": "YWJ",
		"Price": "20900"
	},
	{
		"Category": "PhotoFrame",
		"Color": null,
		"Title": "리츠센 핑크블라썸 xcm 개업선물 캔버스",
		"Link": "https://search.shopping.naver.com/gate.nhn?id=29729031814",
		"Image": "https://shopping-phinf.pstatic.net/main_2972903/29729031814.20211119031707.jpg",
		"Brand": "리츠센",
		"Price": "23000"
	},
	{
		"Category": "PhotoFrame",
		"Color": null,
		"Title": "스피엘 LED액자 조명 인테리어 그림 캔버스 액자 캔뷰 집들이선물",
		"Link": "https://search.shopping.naver.com/gate.nhn?id=12850631588",
		"Image": "https://shopping-phinf.pstatic.net/main_1285063/12850631588.14.jpg",
		"Brand": "스피엘",
		"Price": "27800"
	},
	{
		"Category": "PhotoFrame",
		"Color": null,
		"Title": "해바라기 그림 황금 k 액자 금전운 인테리어 개업 집들이선물 돈들어오는그림",
		"Link": "https://search.shopping.naver.com/gate.nhn?id=83338904034",
		"Image": "https://shopping-phinf.pstatic.net/main_8333890/83338904034.1.jpg",
		"Brand": "",
		"Price": "59000"
	},
	{
		"Category": "PhotoFrame",
		"Color": null,
		"Title": "다루미 패브릭포스터 대형 벽인테리어 액자",
		"Link": "https://search.shopping.naver.com/gate.nhn?id=29861357379",
		"Image": "https://shopping-phinf.pstatic.net/main_2986135/29861357379.20211129042838.jpg",
		"Brand": "다루미",
		"Price": "9700"
	},
	{
		"Category": "PhotoFrame",
		"Color": null,
		"Title": "지누스코 북유럽 감성 인테리어액자 캔버스 패브릭 창문 바다 사진 그림 액자 집들이선물 거리 포스터",
		"Link": "https://search.shopping.naver.com/gate.nhn?id=32754454250",
		"Image": "https://shopping-phinf.pstatic.net/main_3275445/32754454250.20220605084201.jpg",
		"Brand": "지누스코",
		"Price": "3800"
	}
]