[
	{
		"Category": "Stand",
		"Color": "Red",
		"Title": "루미아데코 젤라 원목바디 단 스탠드 레드브라운",
		"Link": "https://search.shopping.naver.com/gate.nhn?id=31426357705",
		"Image": "https://shopping-phinf.pstatic.net/main_3142635/31426357705.20220323003532.jpg",
		"Brand": "",
		"Price": "19840"
	},
	{
		"Category": "Stand",
		"Color": "Red",
		"Title": "스테인글라스 C 빈티지스탠드 레드투명  ",
		"Link": "https://search.shopping.naver.com/gate.nhn?id=34070064010",
		"Image": "https://shopping-phinf.pstatic.net/main_3407006/34070064010.20220814141133.jpg",
		"Brand": "",
		"Price": "83520"
	},
	{
		"Category": "Stand",
		"Color": "Red",
		"Title": "할로윈 단 스탠드 적색",
		"Link": "https://search.shopping.naver.com/gate.nhn?id=23036352500",
		"Image": "https://shopping-phinf.pstatic.net/main_2303635/23036352500.20200603163004.jpg",
		"Brand": "",
		"Price": "100000"
	},
	{
		"Category": "Stand",
		"Color": "Red",
		"Title": "바이빔 주사위 스탠드 레드",
		"Link": "https://search.shopping.naver.com/gate.nhn?id=7541325007",
		"Image": "https://shopping-phinf.pstatic.net/main_7541325/7541325007.20140307100210.jpg",
		"Brand": "바이빔",
		"Price": "68000"
	},
	{
		"Category": "Stand",
		"Color": "Red",
		"Title": "뱅커 뱅크 스탠드 레드로 앤틱 조명 뱅커스탠드 청동",
		"Link": "https://search.shopping.naver.com/gate.nhn?id=32287682446",
		"Image": "https://shopping-phinf.pstatic.net/main_3228768/32287682446.20220512102325.jpg",
		"Brand": "",
		"Price": "29840"
	},
	{
		"Category": "Stand",
		"Color": "Red",
		"Title": "뱅커 뱅크 스탠드 레드로 앤틱 조명 뱅커스탠드 청동",
		"Link": "https://search.shopping.naver.com/gate.nhn?id=32196245705",
		"Image": "https://shopping-phinf.pstatic.net/main_3219624/32196245705.20220506130326.jpg",
		"Brand": "",
		"Price": "28710"
	}
]